bwpfetcher/__init__.py
bwpfetcher/client.py
bwpfetcher/config.py
bwpfetcher/endpoints.py
bwpfetcher/exceptions.py
bwpfetcher/tools/__init__.py
bwpfetcher/tools/achievements.py
bwpfetcher/tools/announcements.py
bwpfetcher/tools/game.py
bwpfetcher/tools/guild.py
bwpfetcher/tools/integration.py
bwpfetcher/tools/leaderboard.py
bwpfetcher/tools/player.py
bwpfetcher-1.1.6.dist-info/METADATA
bwpfetcher-1.1.6.dist-info/WHEEL
bwpfetcher-1.1.6.dist-info/top_level.txt
bwpfetcher-1.1.6.dist-info/RECORD
