Metadata-Version: 2.4
Name: bwpfetcher
Version: 1.1.6
Summary: A library for fetching Voxyl API data
Author-email: Ventros <ventros.development@gmail.com>
Requires-Python: >=3.8
Requires-Dist: aiohttp
Requires-Dist: python-dotenv
